primegenerator/Operators.py
primegenerator/__init__.py
primegenerator/primes.py
primegenerator-1.3.1.dist-info/LICENCE
primegenerator-1.3.1.dist-info/METADATA
primegenerator-1.3.1.dist-info/WHEEL
primegenerator-1.3.1.dist-info/top_level.txt
primegenerator-1.3.1.dist-info/RECORD
