Metadata-Version: 2.1
Name: primegenerator
Version: 1.3.1
Summary: Fast primes generator and related functions
Home-page: https://dev.azure.com/MusicalNinjas/MikesMath/_git/primes
Author: Mike Foster
Author-email: i.am.mike.foster@gmail.com
License: EUPL 1.2
Project-URL: Source, https://dev.azure.com/MusicalNinjas/MikesMath/_git/primes
Project-URL: Info & Requests, https://dev.azure.com/MusicalNinjas/MikesMath
Classifier: Programming Language :: Python :: 3
Classifier: License :: OSI Approved :: European Union Public Licence 1.2 (EUPL 1.2)
Classifier: Operating System :: OS Independent
Classifier: Topic :: Scientific/Engineering :: Mathematics
Classifier: Topic :: Software Development :: Libraries :: Python Modules
Classifier: Intended Audience :: Developers
Classifier: Intended Audience :: Science/Research
Classifier: Intended Audience :: Education
Classifier: Natural Language :: English
Requires-Python: >=3.6
License-File: LICENCE
